WifiDeviceTracker/Detection.py
WifiDeviceTracker/__init__.py
WifiDeviceTracker-0.0.2.dist-info/LICENSE
WifiDeviceTracker-0.0.2.dist-info/METADATA
WifiDeviceTracker-0.0.2.dist-info/WHEEL
WifiDeviceTracker-0.0.2.dist-info/top_level.txt
WifiDeviceTracker-0.0.2.dist-info/RECORD
